uif_client/__init__.py
uif_client/__main__.py
uif_client/client_test.py
uif_client/install.py
uif_client/main.py
uif_client/caddy/caddy_2.3.0_linux_amd64/LICENSE
uif_client/caddy/caddy_2.3.0_linux_amd64/README.md
uif_client/caddy/caddy_2.3.0_linux_amd64/caddy
uif_client/caddy/caddy_2.3.0_windows_amd64/LICENSE
uif_client/caddy/caddy_2.3.0_windows_amd64/README.md
uif_client/caddy/caddy_2.3.0_windows_amd64/caddy.exe
uif_client/caddy_config/tls_ws.caddyfile
uif_client/caddy_config/tls_ws.template
uif_client/controler/contro_linux
uif_client/controler/contro_mac
uif_client/controler/contro_windows.exe
uif_client/controler/readme.md
uif_client/server/.gitignore
uif_client/server/server_main.py
uif_client/v2ray/linux/v2ray-linux-64/config.json
uif_client/v2ray/linux/v2ray-linux-64/geoip.dat
uif_client/v2ray/linux/v2ray-linux-64/geosite.dat
uif_client/v2ray/linux/v2ray-linux-64/v2ctl
uif_client/v2ray/linux/v2ray-linux-64/v2ray
uif_client/v2ray/linux/v2ray-linux-64/vpoint_socks_vmess.json
uif_client/v2ray/linux/v2ray-linux-64/vpoint_vmess_freedom.json
uif_client/v2ray/linux/v2ray-linux-64/systemd/system/v2ray.service
uif_client/v2ray/linux/v2ray-linux-64/systemd/system/v2ray@.service
uif_client/v2ray/windows/v2ray-windows-64/config.json
uif_client/v2ray/windows/v2ray-windows-64/geoip.dat
uif_client/v2ray/windows/v2ray-windows-64/geosite.dat
uif_client/v2ray/windows/v2ray-windows-64/v2ctl.exe
uif_client/v2ray/windows/v2ray-windows-64/v2ray.exe
uif_client/v2ray/windows/v2ray-windows-64/vpoint_socks_vmess.json
uif_client/v2ray/windows/v2ray-windows-64/vpoint_vmess_freedom.json
uif_client/v2ray/windows/v2ray-windows-64/wv2ray.exe
uif_client/v2ray_server_configs/vmess_tls_ws.json
uif_client/v2ray_server_configs/vmess_tls_ws_free.json
uif_client/v2ray_server_configs/vmess_tls_ws_free_ipv6.json
uif_client/v2ray_server_configs/vmess_tls_ws_ipv6.json
hello_world_client_fuck-1620928254.dist-info/METADATA
hello_world_client_fuck-1620928254.dist-info/WHEEL
hello_world_client_fuck-1620928254.dist-info/top_level.txt
hello_world_client_fuck-1620928254.dist-info/RECORD
